tools_tables/__init__.py
tools_tables/modulo.py
tools_tables-0.1.0.dist-info/METADATA
tools_tables-0.1.0.dist-info/WHEEL
tools_tables-0.1.0.dist-info/RECORD
